target_firebase/__init__.py
target_firebase/__main__.py
target_firebase/sinks.py
target_firebase/target.py
target_firebase-0.0.1a5.dist-info/METADATA
target_firebase-0.0.1a5.dist-info/WHEEL
target_firebase-0.0.1a5.dist-info/entry_points.txt
target_firebase-0.0.1a5.dist-info/licenses/LICENSE
target_firebase-0.0.1a5.dist-info/RECORD
