Metadata-Version: 2.4
Name: target-firebase
Version: 0.0.1a5
Summary: Singer target for Firebase, built with the Meltano Singer SDK.
Author-email: Edgar Ramírez-Mondragón <edgarrm358@gmail.com>
License-Expression: Apache-2.0
License-File: LICENSE
Keywords: ELT,Firebase
Classifier: Intended Audience :: Developers
Classifier: License :: OSI Approved :: Apache Software License
Classifier: Operating System :: OS Independent
Classifier: Programming Language :: Python :: 3.12
Classifier: Programming Language :: Python :: 3.13
Classifier: Programming Language :: Python :: 3.14
Requires-Python: >=3.12
Requires-Dist: firebase-admin~=7.1.0
Requires-Dist: singer-sdk[faker]~=0.48.0
Provides-Extra: s3
Requires-Dist: s3fs~=2025.9.0; extra == 's3'
